knowledge_chat/__init__.py
knowledge_chat/_version.py
knowledge_chat/py.typed
knowledge_chat/application/__init__.py
knowledge_chat/application/abstract_knowledge_chat.py
knowledge_chat/application/dto/__init__.py
knowledge_chat/application/dto/conversation_dto.py
knowledge_chat/application/dto/exchange_output_dto.py
knowledge_chat/application/dto/user_dto.py
knowledge_chat/domain/__init__.py
knowledge_chat/domain/error.py
knowledge_chat/domain/model/__init__.py
knowledge_chat/domain/model/conversation.py
knowledge_chat/domain/model/exchange.py
knowledge_chat/domain/model/query.py
knowledge_chat/domain/model/response.py
knowledge_chat/domain/model/thought.py
knowledge_chat/domain/model/user.py
knowledge_chat/domain/service/__init__.py
knowledge_chat/domain/service/domain_service_registry.py
knowledge_chat/domain/service/response_agent.py
knowledge_chat/infrastructure/__init__.py
knowledge_chat/infrastructure/application/__init__.py
knowledge_chat/infrastructure/application/knowledge_chat.py
knowledge_chat/infrastructure/domain/__init__.py
knowledge_chat/infrastructure/domain/service/__init__.py
knowledge_chat/infrastructure/domain/service/domain_service_registry.py
knowledge_chat/infrastructure/domain/service/langchain_kshot_response_agent.py
knowledge_chat/infrastructure/persistence/__init__.py
knowledge_chat/infrastructure/persistence/transcoding.py
knowledge_chat/infrastructure/settings/__init__.py
knowledge_chat/infrastructure/settings/_base_settings.py
knowledge_chat/infrastructure/settings/agent_settings.py
knowledge_chat/infrastructure/settings/azure_openai_settings.py
knowledge_chat/infrastructure/settings/neo4j_settings.py
knowledge_chat/infrastructure/settings/ollama_settings.py
knowledge_chat-0.1.0.dist-info/METADATA
knowledge_chat-0.1.0.dist-info/WHEEL
knowledge_chat-0.1.0.dist-info/licenses/LICENSE
knowledge_chat-0.1.0.dist-info/RECORD
