Metadata-Version: 2.3
Name: knowledge-chat
Version: 0.1.0
Summary: A framework to enable retrieval augmented generation (RAG) with knowledge graphs for chat applications.
Project-URL: Homepage, https://github.com/Midnighter/knowledge-chat
Project-URL: Documentation, https://knowledge-chat.readthedocs.io
Project-URL: Source Code, https://github.com/Midnighter/knowledge-chat
Project-URL: Bug Tracker, https://github.com/Midnighter/knowledge-chat/issues
Project-URL: Download, https://pypi.org/project/knowledge-chat/#files
Author-email: "Moritz E. Beber" <midnighter@posteo.net>
License: Apache-2.0
Keywords: chainlit,event-sourcing,genai,genai-chatbot,graph-rag,knowledge-graph,langchain,llm,neo4j,rag
Classifier: Development Status :: 2 - Pre-Alpha
Classifier: Intended Audience :: Science/Research
Classifier: License :: OSI Approved :: Apache Software License
Classifier: Natural Language :: English
Classifier: Operating System :: OS Independent
Classifier: Programming Language :: Python :: 3 :: Only
Classifier: Programming Language :: Python :: 3.12
Classifier: Programming Language :: Python :: 3.13
Classifier: Topic :: Scientific/Engineering
Classifier: Typing :: Typed
Requires-Python: >=3.12
Requires-Dist: eventsourcing~=9.3
Requires-Dist: langchain-community~=0.3
Requires-Dist: langchain~=0.3
Requires-Dist: neo4j~=5.26
Requires-Dist: pydantic-settings~=2.6
Requires-Dist: pydantic~=2.9
Requires-Dist: structlog~=24.4
Provides-Extra: ollama
Requires-Dist: langchain-ollama~=0.2; extra == 'ollama'
Provides-Extra: openai
Requires-Dist: langchain-openai~=0.2; extra == 'openai'
